netbox_docker_plugin/__init__.py
netbox_docker_plugin/filtersets.py
netbox_docker_plugin/navigation.py
netbox_docker_plugin/signals.py
netbox_docker_plugin/tables.py
netbox_docker_plugin/urls.py
netbox_docker_plugin/api/__init__.py
netbox_docker_plugin/api/renderers.py
netbox_docker_plugin/api/serializers.py
netbox_docker_plugin/api/urls.py
netbox_docker_plugin/api/views.py
netbox_docker_plugin/forms/__init__.py
netbox_docker_plugin/forms/bind.py
netbox_docker_plugin/forms/container.py
netbox_docker_plugin/forms/device.py
netbox_docker_plugin/forms/env.py
netbox_docker_plugin/forms/host.py
netbox_docker_plugin/forms/image.py
netbox_docker_plugin/forms/label.py
netbox_docker_plugin/forms/log_driver_option.py
netbox_docker_plugin/forms/mount.py
netbox_docker_plugin/forms/network.py
netbox_docker_plugin/forms/network_setting.py
netbox_docker_plugin/forms/port.py
netbox_docker_plugin/forms/registry.py
netbox_docker_plugin/forms/sysctl.py
netbox_docker_plugin/forms/volume.py
netbox_docker_plugin/migrations/0001_initial.py
netbox_docker_plugin/migrations/0002_image.py
netbox_docker_plugin/migrations/0003_image_size.py
netbox_docker_plugin/migrations/0004_volume.py
netbox_docker_plugin/migrations/0005_network.py
netbox_docker_plugin/migrations/0006_container_port_mount_label_env_and_more.py
netbox_docker_plugin/migrations/0007_remove_container_netbox_docker_plugin_container_unique_name_host__and_more.py
netbox_docker_plugin/migrations/0008_alter_network_unique_together_network_networkid_and_more.py
netbox_docker_plugin/migrations/0009_remove_container_network_networksettings_and_more.py
netbox_docker_plugin/migrations/0010_container_containerid_and_more.py
netbox_docker_plugin/migrations/0011_host_token.py
netbox_docker_plugin/migrations/0012_host_state.py
netbox_docker_plugin/migrations/0013_host_netbox_url.py
netbox_docker_plugin/migrations/0014_container_operation.py
netbox_docker_plugin/migrations/0015_remove_mount_netbox_docker_plugin_mount_unique_volume_and_more.py
netbox_docker_plugin-4.11.0.dist-info/licenses/LICENSE
netbox_docker_plugin-4.11.0.dist-info/METADATA
netbox_docker_plugin-4.11.0.dist-info/WHEEL
netbox_docker_plugin-4.11.0.dist-info/top_level.txt
netbox_docker_plugin-4.11.0.dist-info/RECORD
