Metadata-Version: 2.4
Name: netbox-docker-plugin
Version: 4.11.0
Summary: Manage Docker with Netbox & style.
Author-email: Vincent Simonin <vincent@saashup.com>, David Delassus <david.jose.delassus@gmail.com>
Project-URL: Homepage, https://github.com/SaaShup/netbox-docker-plugin
Project-URL: Bug Tracker, https://github.com/SaaShup/netbox-docker-plugin/issues
Keywords: netbox,netbox-plugin,docker
Classifier: Programming Language :: Python :: 3
Requires-Python: >=3.11
License-File: LICENSE
Dynamic: license-file
